logyca_azure_storage_blob/__init__.py
logyca_azure_storage_blob/utils/__init__.py
logyca_azure_storage_blob/utils/helpers/__init__.py
logyca_azure_storage_blob/utils/helpers/azure_storage_account_blob_management.py
logyca_azure_storage_blob/utils/helpers/file_analyzer.py
logyca_azure_storage_blob-0.3.0.dist-info/METADATA
logyca_azure_storage_blob-0.3.0.dist-info/WHEEL
logyca_azure_storage_blob-0.3.0.dist-info/RECORD
