Metadata-Version: 2.4
Name: logyca-azure-storage-blob
Version: 0.3.0
Summary: An integration package created by the company LOGYCA to interact with the blob container files in your Azure Storage account.
Project-URL: homepage, https://github.com/logyca/python-libraries/tree/main/logyca-azure-storage-blob
Author-email: Jaime Andres Cardona Carrillo <jacardona@outlook.com>
Keywords: azure,blob,download,storage,upload
Classifier: Development Status :: 4 - Beta
Classifier: Intended Audience :: Developers
Classifier: Intended Audience :: Information Technology
Classifier: Intended Audience :: System Administrators
Classifier: Operating System :: OS Independent
Classifier: Programming Language :: Python :: 3 :: Only
Classifier: Programming Language :: Python :: 3.8
Classifier: Programming Language :: Python :: 3.9
Classifier: Programming Language :: Python :: 3.10
Classifier: Programming Language :: Python :: 3.11
Classifier: Topic :: Database
Classifier: Topic :: Database :: Front-Ends
Classifier: Topic :: Software Development
Classifier: Topic :: Software Development :: Libraries
Classifier: Topic :: Software Development :: Libraries :: Python Modules
Classifier: Typing :: Typed
Requires-Python: >=3.8
Requires-Dist: azure-storage-blob>=12.20.0
